BM16036UNO/__init__.py
BM16036UNO/biseccion.py
BM16036UNO/cramer.py
BM16036UNO/descomposicion_lu.py
BM16036UNO/eliminacion_gaussiana.py
BM16036UNO/gauss_jordan.py
BM16036UNO/gauss_seidel.py
BM16036UNO/jacobi.py
bm16036uno-0.1.2.dist-info/METADATA
bm16036uno-0.1.2.dist-info/WHEEL
bm16036uno-0.1.2.dist-info/top_level.txt
bm16036uno-0.1.2.dist-info/RECORD
