Metadata-Version: 2.4
Name: BM16036UNO
Version: 0.1.2
Summary: Librería para resolver sistemas de ecuaciones lineales y no lineales mediante varios métodos.
Home-page: https://github.com/bm16036/BM16036UNO.git
Author: Erick Alexander Borja Mauricio
Author-email: bm16036@ues.edu.sv
Requires-Python: >=3.6
Requires-Dist: numpy>=1.18.0
Dynamic: author
Dynamic: author-email
Dynamic: description
Dynamic: description-content-type
Dynamic: home-page
Dynamic: requires-dist
Dynamic: requires-python
Dynamic: summary
